ppgl/ppgl.py
ppgl-1.0.1.dist-info/LICENSE
ppgl-1.0.1.dist-info/METADATA
ppgl-1.0.1.dist-info/WHEEL
ppgl-1.0.1.dist-info/top_level.txt
ppgl-1.0.1.dist-info/RECORD
