Metadata-Version: 2.1
Name: ppgl
Version: 1.0.1
Summary: A tkinter library that juts works
Home-page: https://github.com/0xleft/ppgl
Author: 0xleft
Author-email: test@test.com
License: MIT
License-File: LICENSE
